arraylib/__init__.py
arraylib/alignment.py
arraylib/config.py
arraylib/deconvolution.py
arraylib/generate_count_matrix.py
arraylib/io.py
arraylib/libraryexperiment.py
arraylib/main.py
arraylib/predict_locations.py
arraylib/simulations.py
arraylib/trimming.py
arraylib_solve-1.0.0.dist-info/WHEEL
arraylib_solve-1.0.0.dist-info/entry_points.txt
arraylib_solve-1.0.0.dist-info/METADATA
arraylib_solve-1.0.0.dist-info/RECORD
